var = ntucdata {"type":"FeatureCollection","features":[{"type":"Feature","properties":{"marker-color":"#7e7e7e","marker-size":"medium","marker-symbol":"","store":"FairPrice Punggol Drive","address":"612 Punggol Dr., 01-06 Damai Grove, Singapore 820612"},"geometry":{"type":"Point","coordinates":[103.90852779150009,1.4048646648792043]}},{"type":"Feature","properties":{"marker-color":"#7e7e7e","marker-size":"medium","marker-symbol":"","store":"FairPrice Punggol Walk","address":"308C Punggol Walk, #01-352, Singapore 823308"},"geometry":{"type":"Point","coordinates":[103.89910720288754,1.408278758465169]}}]}